.travis.yml
LICENSE
MANIFEST.in
README.rst
requirements.txt
setup.cfg
setup.py
./iplantuml/__init__.py
IPlantUML.egg-info/PKG-INFO
IPlantUML.egg-info/SOURCES.txt
IPlantUML.egg-info/dependency_links.txt
IPlantUML.egg-info/entry_points.txt
IPlantUML.egg-info/not-zip-safe
IPlantUML.egg-info/requires.txt
IPlantUML.egg-info/top_level.txt